[{"weight_name": "dense_67/kernel:0", "length": 416, "shape": [13, 32], "layer_name": "dense_67", "offset": 0, "type": "float32"}, {"weight_name": "dense_67/bias:0", "length": 32, "shape": [32], "layer_name": "dense_67", "offset": 1664, "type": "float32"}, {"weight_name": "dense_68/kernel:0", "length": 1024, "shape": [32, 32], "layer_name": "dense_68", "offset": 1792, "type": "float32"}, {"weight_name": "dense_68/bias:0", "length": 32, "shape": [32], "layer_name": "dense_68", "offset": 5888, "type": "float32"}, {"weight_name": "dense_69/kernel:0", "length": 1024, "shape": [32, 32], "layer_name": "dense_69", "offset": 6016, "type": "float32"}, {"weight_name": "dense_69/bias:0", "length": 32, "shape": [32], "layer_name": "dense_69", "offset": 10112, "type": "float32"}, {"weight_name": "dense_70/kernel:0", "length": 1024, "shape": [32, 32], "layer_name": "dense_70", "offset": 10240, "type": "float32"}, {"weight_name": "dense_70/bias:0", "length": 32, "shape": [32], "layer_name": "dense_70", "offset": 14336, "type": "float32"}, {"weight_name": "dense_71/kernel:0", "length": 1024, "shape": [32, 32], "layer_name": "dense_71", "offset": 14464, "type": "float32"}, {"weight_name": "dense_71/bias:0", "length": 32, "shape": [32], "layer_name": "dense_71", "offset": 18560, "type": "float32"}, {"weight_name": "dense_72/kernel:0", "length": 64, "shape": [32, 2], "layer_name": "dense_72", "offset": 18688, "type": "float32"}, {"weight_name": "dense_72/bias:0", "length": 2, "shape": [2], "layer_name": "dense_72", "offset": 18944, "type": "float32"}]